main.py
ai01_dev-0.0.1.dist-info/licenses/LICENSE
ai01_dev-0.0.1.dist-info/METADATA
ai01_dev-0.0.1.dist-info/WHEEL
ai01_dev-0.0.1.dist-info/top_level.txt
ai01_dev-0.0.1.dist-info/RECORD
