Metadata-Version: 2.4
Name: ai01-dev
Version: 0.0.1
Summary: Add your description here
Project-URL: Homepage, https://github.com/cobuild-tech/ai01
Classifier: Programming Language :: Python :: 3
Classifier: License :: OSI Approved :: MIT License
Classifier: Operating System :: OS Independent
Requires-Python: >=3.9
License-File: LICENSE
Requires-Dist: pip>=25.3
Dynamic: license-file
